<SOUI name="dlg_emaPara" title="EMA参数" bigIcon="ICON_LOGO:32" smallIcon="ICON_LOGO:16" width="365" height="180" margin="1,5,5,5" wndType="normal" toolWindow="0">
	<root cache="1">
		<window pos="0,0,-0,-0" colorBkgnd="rgb(70,70,70)" colorText="#ffffff">
			<caption pos="0,0,-0,30" focusable="1" drawfocusrect="0">
				<text pos="5,4" name="txt_title">EMA参数</text>
				<imgbtn name="btn_EMAClose" skin="_skin.sys.btn.close" pos="-45,0" tip="close" animate="1" />
			</caption>
			<edit name="edit_EMAPara1" pos="92,60" size="72, 24" colorBkgnd="#FFFFFF" cueText="" colorText="#000000" number="1" />
			<text pos="48,60" size="40, 24">参数1</text>
			<edit name="edit_EMAPara2" pos="244,60" size="72, 24" colorBkgnd="#FFFFFF" cueText="" colorText="#000000" number="1" />
			<text pos="200,60" size="40, 24">参数2</text>
			<button name="btn_EMAOK" pos="50,140" size="100, 24" colorText="#000000" skin="_skin.sys.btn.normal">确定</button>
			<button name="btn_EMACancel" pos="220,140" size="100,24" colorText="#000000" skin="_skin.sys.btn.normal">取消</button>
			<button name="btn_EMADefault" pos="50,100" size="100,24" colorText="#000000" skin="_skin.sys.btn.normal">默认参数</button>
			<button name="btn_EMASetDefault" pos="220,100" size="100,24" colorText="#000000" skin="_skin.sys.btn.normal">设置默认参数</button>
		</window>
	</root>
</SOUI>
